coderHub/__init__.py
coderHub/coderhub.py
coderHub-1.0.7.dist-info/LICENSE
coderHub-1.0.7.dist-info/METADATA
coderHub-1.0.7.dist-info/WHEEL
coderHub-1.0.7.dist-info/top_level.txt
coderHub-1.0.7.dist-info/RECORD
