Metadata-Version: 2.1
Name: coderHub
Version: 1.0.7
Summary: A python method based on the API of the coderHub.sa, which helps you to fetch the challenges and more
Home-page: https://github.com/Awiteb/coderHub
Author: Awiteb
Author-email: Awiteb@hotmail.com
License: UNKNOWN
Keywords: coderHub,programming challenges,challenges
Platform: UNKNOWN
Classifier: Programming Language :: Python :: 3.7
Classifier: Programming Language :: Python :: 3.8
Classifier: Programming Language :: Python :: 3.9
Classifier: Programming Language :: Python :: 3.10
Classifier: License :: OSI Approved :: GNU General Public License v3 (GPLv3)
Classifier: Operating System :: OS Independent
Requires-Python: >=3.7
License-File: LICENSE
Requires-Dist: certifi (==2021.5.30)
Requires-Dist: chardet (==4.0.0)
Requires-Dist: idna (==2.10)
Requires-Dist: requests (==2.25.1)
Requires-Dist: urllib3 (==1.26.6)
